<?xml version="1.0" encoding="UTF-8"?>
<odoo noupdate="1">

    <record id="income_statement_summary" model="mis.report">
        <field name="name">Income Statement (Summary)</field>
        <field name="description">Income statement without details</field>
        <field name="exclude_closing_entries" eval="True"/>
        <field name="kpi_ids" eval="[
            (5, 0),
            (0, 0, {
                'name': 'INC',
                'description': 'Revenues',
                'expression': '-bal[(&#34;account_type&#34;, &#34;=&#34;, &#34;income&#34;)][]',
                'style_id': ref('canada_mis_report.style_h3'),
                'accumulation_method': 'sum',
                'compare_method': 'pct',
                'type': 'num',
                'auto_expand_accounts': False,
            }),
            (0, 0, {
                'name': 'CGS',
                'description': 'CGS - Cost of Goods Sold',
                'expression': '-bal[(&#34;account_type&#34;, &#34;=&#34;, &#34;expense_direct_cost&#34;)][]',
                'style_id': ref('canada_mis_report.style_h3'),
                'accumulation_method': 'sum',
                'compare_method': 'pct',
                'type': 'num',
                'auto_expand_accounts': False,
            }),
            (0, 0, {
                'name': 'GROSS_PROFIT',
                'description': 'Gross Profit',
                'expression': 'INC + CGS',
                'style_id': ref('canada_mis_report.style_h2'),
                'accumulation_method': 'sum',
                'compare_method': 'pct',
                'type': 'num',
                'auto_expand_accounts': False,
            }),
            (0, 0, {
                'name': 'INDIRECT_COSTS',
                'description': 'Indirect Costs',
                'expression': '-bal[(&#34;account_type&#34;, &#34;in&#34;, &#34;expense&#34;, &#34;expense_depreciation&#34;)][]',
                'style_id': ref('canada_mis_report.style_h3'),
                'accumulation_method': 'sum',
                'compare_method': 'pct',
                'type': 'num',
                'auto_expand_accounts': False,
            }),
            (0, 0, {
                'name': 'EBIT',
                'description': 'EBIT - Earnings Before Interests And Taxes',
                'expression': 'GROSS_PROFIT + INDIRECT_COSTS',
                'style_id': ref('canada_mis_report.style_h2'),
                'accumulation_method': 'sum',
                'compare_method': 'pct',
                'type': 'num',
                'auto_expand_accounts': False,
            }),
            (0, 0, {
                'name': 'INTEREST',
                'description': 'Interests',
                'expression': '-bal[(&#34;account_type&#34;, &#34;=&#34;, &#34;interest_expenses&#34;)][]',
                'style_id': ref('canada_mis_report.style_h3'),
                'accumulation_method': 'sum',
                'compare_method': 'pct',
                'type': 'num',
                'auto_expand_accounts': False,
            }),
            (0, 0, {
                'name': 'ONE_TIME_CHARGES',
                'description': 'One-time Charges',
                'expression': '-bal[(&#34;account_type&#34;, &#34;=&#34;, &#34;one_time_expenses&#34;)][]',
                'style_id': ref('canada_mis_report.style_h3'),
                'accumulation_method': 'sum',
                'compare_method': 'pct',
                'type': 'num',
                'auto_expand_accounts': False,
            }),
            (0, 0, {
                'name': 'ONE_TIME_REVENUES',
                'description': 'One-time Revenues',
                'expression': '-bal[(&#34;account_type&#34;, &#34;=&#34;, &#34;income_other&#34;)][]',
                'style_id': ref('canada_mis_report.style_h3'),
                'accumulation_method': 'sum',
                'compare_method': 'pct',
                'type': 'num',
                'auto_expand_accounts': False,
            }),
            (0, 0, {
                'name': 'EBT',
                'description': 'EBT - Earnings Before Taxes',
                'expression': 'EBIT + INTEREST + ONE_TIME_CHARGES + ONE_TIME_REVENUES',
                'style_id': ref('canada_mis_report.style_h2'),
                'accumulation_method': 'sum',
                'compare_method': 'pct',
                'type': 'num',
                'auto_expand_accounts': False,
            }),
            (0, 0, {
                'name': 'TAXES',
                'description': 'Taxes',
                'expression': '-bal[(&#34;account_type&#34;, &#34;=&#34;, &#34;tax_expenses&#34;)][]',
                'style_id': ref('canada_mis_report.style_h3'),
                'accumulation_method': 'sum',
                'compare_method': 'pct',
                'type': 'num',
                'auto_expand_accounts': False,
            }),
            (0, 0, {
                'name': 'NET_PROFIT',
                'description': 'Net Profit',
                'expression': 'EBT + TAXES',
                'style_id': ref('canada_mis_report.style_h1'),
                'accumulation_method': 'sum',
                'compare_method': 'pct',
                'type': 'num',
                'auto_expand_accounts': False,
            }),
        ]"/>
    </record>

    <record id="income_statement_detailed" model="mis.report">
        <field name="name">Income Statement (Detailed)</field>
        <field name="description">Income statement with details</field>
        <field name="exclude_closing_entries" eval="True"/>
        <field name="kpi_ids" eval="[
            (5, 0),
            (0, 0, {
                'name': 'INC',
                'description': 'Revenues',
                'expression': '-bal[(&#34;account_type&#34;, &#34;=&#34;, &#34;income&#34;)][]',
                'style_id': ref('canada_mis_report.style_h3'),
                'accumulation_method': 'sum',
                'compare_method': 'pct',
                'type': 'num',
                'auto_expand_accounts': True,
                'auto_expand_accounts_style_id': ref('canada_mis_report.style_detail'),
            }),
            (0, 0, {
                'name': 'CGS',
                'description': 'CGS - Cost of Goods Sold',
                'expression': '-bal[(&#34;account_type&#34;, &#34;=&#34;, &#34;expense_direct_cost&#34;)][]',
                'style_id': ref('canada_mis_report.style_h3'),
                'accumulation_method': 'sum',
                'compare_method': 'pct',
                'type': 'num',
                'auto_expand_accounts': True,
                'auto_expand_accounts_style_id': ref('canada_mis_report.style_detail'),
            }),
            (0, 0, {
                'name': 'GROSS_PROFIT',
                'description': 'Gross Profit',
                'expression': 'INC + CGS',
                'style_id': ref('canada_mis_report.style_h2'),
                'accumulation_method': 'sum',
                'compare_method': 'pct',
                'type': 'num',
                'auto_expand_accounts': False,
            }),
            (0, 0, {
                'name': 'INDIRECT_COSTS',
                'description': 'Indirect Costs',
                'expression': '-bal[(&#34;account_type&#34;, &#34;in&#34;, &#34;expenses&#34;, &#34;expense_depreciation&#34;))][]',
                'style_id': ref('canada_mis_report.style_h3'),
                'accumulation_method': 'sum',
                'compare_method': 'pct',
                'type': 'num',
                'auto_expand_accounts': True,
                'auto_expand_accounts_style_id': ref('canada_mis_report.style_detail'),
            }),
            (0, 0, {
                'name': 'EBIT',
                'description': 'EBIT - Earnings Before Interests And Taxes',
                'expression': 'GROSS_PROFIT + INDIRECT_COSTS',
                'style_id': ref('canada_mis_report.style_h2'),
                'accumulation_method': 'sum',
                'compare_method': 'pct',
                'type': 'num',
                'auto_expand_accounts': False,
            }),
            (0, 0, {
                'name': 'INTEREST',
                'description': 'Interests',
                'expression': '-bal[(&#34;account_type&#34;, &#34;=&#34;, &#34;interest_expenses&#34;)][]',
                'style_id': ref('canada_mis_report.style_h3'),
                'accumulation_method': 'sum',
                'compare_method': 'pct',
                'type': 'num',
                'auto_expand_accounts': True,
                'auto_expand_accounts_style_id': ref('canada_mis_report.style_detail'),
            }),
            (0, 0, {
                'name': 'ONE_TIME_CHARGES',
                'description': 'One-time Charges',
                'expression': '-bal[(&#34;account_type&#34;, &#34;=&#34;, &#34;one_time_expenses&#34;)][]',
                'style_id': ref('canada_mis_report.style_h3'),
                'accumulation_method': 'sum',
                'compare_method': 'pct',
                'type': 'num',
                'auto_expand_accounts': True,
                'auto_expand_accounts_style_id': ref('canada_mis_report.style_detail'),
            }),
            (0, 0, {
                'name': 'ONE_TIME_REVENUES',
                'description': 'One-time Revenues',
                'expression': '-bal[(&#34;account_type&#34;, &#34;=&#34;, &#34;income_other&#34;)][]',
                'style_id': ref('canada_mis_report.style_h3'),
                'accumulation_method': 'sum',
                'compare_method': 'pct',
                'type': 'num',
                'auto_expand_accounts': True,
                'auto_expand_accounts_style_id': ref('canada_mis_report.style_detail'),
            }),
            (0, 0, {
                'name': 'EBT',
                'description': 'EBT - Earnings Before Taxes',
                'expression': 'EBIT + INTEREST + ONE_TIME_CHARGES + ONE_TIME_REVENUES',
                'style_id': ref('canada_mis_report.style_h2'),
                'accumulation_method': 'sum',
                'compare_method': 'pct',
                'type': 'num',
                'auto_expand_accounts': False,
            }),
            (0, 0, {
                'name': 'TAXES',
                'description': 'Taxes',
                'expression': '-bal[(&#34;account_type&#34;, &#34;=&#34;, &#34;tax_expenses&#34;)][]',
                'style_id': ref('canada_mis_report.style_h3'),
                'accumulation_method': 'sum',
                'compare_method': 'pct',
                'type': 'num',
                'auto_expand_accounts': False,
            }),
            (0, 0, {
                'name': 'NET_PROFIT',
                'description': 'Net Profit',
                'expression': 'EBT + TAXES',
                'style_id': ref('canada_mis_report.style_h1'),
                'accumulation_method': 'sum',
                'compare_method': 'pct',
                'type': 'num',
                'auto_expand_accounts': False,
            }),
        ]"/>
    </record>

    <record id="balance_sheet_summary" model="mis.report">
        <field name="name">Balance Sheet (Summary)</field>
        <field name="description">Balance sheet without details</field>
        <field name="subreport_ids" eval="[
            (5, 0),
            (0, 0, {
                'name': 'ER',
                'subreport_id': ref('canada_mis_report.income_statement_summary'),                          
            }),
        ]"/>
        <field name="kpi_ids" eval="[
            (5, 0),
            (0, 0, {
                'name': 'TITLE_ASSETS',
                'description': 'Assets',
                'expression': 'AccountingNone',
                'style_id': ref('canada_mis_report.style_h1'),
                'accumulation_method': 'sum',
                'compare_method': 'pct',
                'type': 'num',
                'auto_expand_accounts': False,
            }),
            (0, 0, {
                'name': 'LIQUIDITY',
                'description': 'Liquidity',
                'expression': 'bale[(&#34;account_type&#34;, &#34;=&#34;, &#34;asset_cash&#34;)][]',
                'style_id': ref('canada_mis_report.style_h3'),
                'accumulation_method': 'sum',
                'compare_method': 'pct',
                'type': 'num',
                'auto_expand_accounts': False,
            }),
            (0, 0, {
                'name': 'RECEIVABLE',
                'description': 'Accounts Receivable',
                'expression': 'bale[(&#34;account_type&#34;, &#34;=&#34;, &#34;asset_receivable&#34;)][]',
                'style_id': ref('canada_mis_report.style_h3'),
                'accumulation_method': 'sum',
                'compare_method': 'pct',
                'type': 'num',
                'auto_expand_accounts': False,
            }),
            (0, 0, {
                'name': 'PRE_PAID_EXPENSES',
                'description': 'Pre-paid Expenses',
                'expression': 'bale[(&#34;account_type&#34;, &#34;=&#34;, &#34;asset_prepayments&#34;)][]',
                'style_id': ref('canada_mis_report.style_h3'),
                'accumulation_method': 'sum',
                'compare_method': 'pct',
                'type': 'num',
                'auto_expand_accounts': False,
            }),
            (0, 0, {
                'name': 'OTHER_CURRENT_ASSETS',
                'description': 'Other Current Assets',
                'expression': 'bale[(&#34;account_type&#34;, &#34;=&#34;, &#34;asset_current&#34;)][]',
                'style_id': ref('canada_mis_report.style_h3'),
                'accumulation_method': 'sum',
                'compare_method': 'pct',
                'type': 'num',
                'auto_expand_accounts': False,
            }),
            (0, 0, {
                'name': 'TOTAL_CURRENT_ASSETS',
                'description': 'Total Current Assets',
                'expression': 'LIQUIDITY + RECEIVABLE + PRE_PAID_EXPENSES + OTHER_CURRENT_ASSETS',
                'style_id': ref('canada_mis_report.style_h2'),
                'accumulation_method': 'sum',
                'compare_method': 'pct',
                'type': 'num',
                'auto_expand_accounts': False,
            }),
            (0, 0, {
                'name': 'FIXED_ASSETS',
                'description': 'Fixed Assets',
                'expression': 'bale[(&#34;account_type&#34;, &#34;=&#34;, &#34;asset_fixed&#34;)][]',
                'style_id': ref('canada_mis_report.style_h3'),
                'accumulation_method': 'sum',
                'compare_method': 'pct',
                'type': 'num',
                'auto_expand_accounts': False,
            }),
            (0, 0, {
                'name': 'OTHER_NON_CURRENT_ASSETS',
                'description': 'Other Non-current Assets',
                'expression': 'bale[(&#34;account_type&#34;, &#34;=&#34;, &#34;asset_non_current&#34;)][]',
                'style_id': ref('canada_mis_report.style_h3'),
                'accumulation_method': 'sum',
                'compare_method': 'pct',
                'type': 'num',
                'auto_expand_accounts': False,
            }),
            (0, 0, {
                'name': 'TOTAL_NON_CURRENT_ASSETS',
                'description': 'Total Non-current Assets',
                'expression': 'FIXED_ASSETS + OTHER_NON_CURRENT_ASSETS',
                'style_id': ref('canada_mis_report.style_h2'),
                'accumulation_method': 'sum',
                'compare_method': 'pct',
                'type': 'num',
                'auto_expand_accounts': False,
            }),
            (0, 0, {
                'name': 'TOTAL_ASSETS',
                'description': 'Total Assets',
                'expression': 'TOTAL_CURRENT_ASSETS + TOTAL_NON_CURRENT_ASSETS',
                'style_id': ref('canada_mis_report.style_h1'),
                'accumulation_method': 'sum',
                'compare_method': 'pct',
                'type': 'num',
                'auto_expand_accounts': False,
            }),
            (0, 0, {
                'name': '_13',
                'description': '-',
                'expression': 'AccountingNone',
                'accumulation_method': 'sum',
                'compare_method': 'pct',
                'type': 'num',
                'auto_expand_accounts': False,
            }),
            (0, 0, {
                'name': 'TITLE_LIABILITIES',
                'description': 'Liabilities',
                'expression': 'AccountingNone',
                'style_id': ref('canada_mis_report.style_h1'),
                'accumulation_method': 'sum',
                'compare_method': 'pct',
                'type': 'num',
                'auto_expand_accounts': False,
            }),
            (0, 0, {
                'name': 'PAYABLE',
                'description': 'Accounts Payable',
                'expression': '-bale[(&#34;account_type&#34;, &#34;=&#34;, &#34;liability_payable&#34;)][]',
                'style_id': ref('canada_mis_report.style_h3'),
                'accumulation_method': 'sum',
                'compare_method': 'pct',
                'type': 'num',
                'auto_expand_accounts': False,
            }),
            (0, 0, {
                'name': 'CREDIT_CARDS',
                'description': 'Credit Cards',
                'expression': '-bale[(&#34;account_type&#34;, &#34;=&#34;, &#34;liability_credit_card&#34;)][]',
                'style_id': ref('canada_mis_report.style_h3'),
                'accumulation_method': 'sum',
                'compare_method': 'pct',
                'type': 'num',
                'auto_expand_accounts': False,
            }),
            (0, 0, {
                'name': 'OTHER_CURRENT_LIABILITIES',
                'description': 'Other Current Liabilities',
                'expression': '-bale[(&#34;account_type&#34;, &#34;=&#34;, &#34;liability_current&#34;)][]',
                'style_id': ref('canada_mis_report.style_h3'),
                'accumulation_method': 'sum',
                'compare_method': 'pct',
                'type': 'num',
                'auto_expand_accounts': False,
            }),
            (0, 0, {
                'name': 'NON_CURRENT_LIABILITIES',
                'description': 'Non-current Liabilities',
                'expression': '-bale[(&#34;account_type&#34;, &#34;=&#34;, &#34;liability_non_current&#34;)][]',
                'style_id': ref('canada_mis_report.style_h3'),
                'accumulation_method': 'sum',
                'compare_method': 'pct',
                'type': 'num',
                'auto_expand_accounts': False,
            }),
            (0, 0, {
                'name': 'TOTAL_LIABILITIES',
                'description': 'Total Liabilities',
                'expression': 'PAYABLE + CREDIT_CARDS + OTHER_CURRENT_LIABILITIES + NON_CURRENT_LIABILITIES',
                'style_id': ref('canada_mis_report.style_h2'),
                'accumulation_method': 'sum',
                'compare_method': 'pct',
                'type': 'num',
                'auto_expand_accounts': False,
            }),
            (0, 0, {
                'name': '_15',
                'description': '-',
                'expression': 'AccountingNone',
                'accumulation_method': 'sum',
                'compare_method': 'pct',
                'type': 'num',
                'auto_expand_accounts': False,
            }),
            (0, 0, {
                'name': 'TITLE_EQUITY',
                'description': 'Equity',
                'expression': 'AccountingNone',
                'style_id': ref('canada_mis_report.style_h1'),
                'accumulation_method': 'sum',
                'compare_method': 'pct',
                'type': 'num',
                'auto_expand_accounts': False,
            }),
            (0, 0, {
                'name': 'EQUITY',
                'description': 'Equity and Previous Years Retained Earnings',
                'expression': '-bale[(&#34;account_type&#34;, &#34;in&#34;, (&#34;equity&#34;, &#34;equity_unaffected&#34;))][]',
                'style_id': ref('canada_mis_report.style_h3'),
                'accumulation_method': 'sum',
                'compare_method': 'pct',
                'type': 'num',
                'auto_expand_accounts': False,
            }),
            (0, 0, {
                'name': 'UNDEFERRED_RESULT_CURRENT',
                'description': 'Undeferred Profit And Loss - Current Year',
                'expression': 'YEAR_RESULT + RESULT_REPORTED',
                'style_id': ref('canada_mis_report.style_h3'),
                'accumulation_method': 'sum',
                'compare_method': 'pct',
                'type': 'num',
                'auto_expand_accounts': False,
            }),
            (0, 0, {
                'name': 'YEAR_RESULT',
                'description': 'Year Result',
                'expression': 'ER.NET_PROFIT',
                'style_id': ref('canada_mis_report.style_detail'),
                'accumulation_method': 'sum',
                'compare_method': 'pct',
                'type': 'num',
                'auto_expand_accounts': False,
            }),
            (0, 0, {
                'name': 'RESULT_REPORTED',
                'description': 'Deferred Results',
                'expression': '-balp[(&#34;account_type&#34;, &#34;=&#34;, &#34;equity_unaffected&#34;)][]',
                'style_id': ref('canada_mis_report.style_detail'),
                'accumulation_method': 'sum',
                'compare_method': 'pct',
                'type': 'num',
                'auto_expand_accounts': False,
            }),
            (0, 0, {
                'name': 'TOTAL_EQUITY',
                'description': 'Total Equity',
                'expression': 'EQUITY + UNDEFERRED_RESULT_CURRENT',
                'style_id': ref('canada_mis_report.style_h2'),
                'accumulation_method': 'sum',
                'compare_method': 'pct',
                'type': 'num',
                'auto_expand_accounts': False,
            }),
            (0, 0, {
                'name': 'TOTAL_EQUITY_LIABILITIES',
                'description': 'Total Equity And Liabilities',
                'expression': 'TOTAL_EQUITY + TOTAL_LIABILITIES',
                'style_id': ref('canada_mis_report.style_h1'),
                'accumulation_method': 'sum',
                'compare_method': 'pct',
                'type': 'num',
                'auto_expand_accounts': False,
            }),
        ]"/>
    </record>

    <record id="balance_sheet_detailed" model="mis.report">
        <field name="name">Balance Sheet (Detailed)</field>
        <field name="description">Balance sheet with details</field>
        <field name="subreport_ids" eval="[
            (5, 0),
            (0, 0, {
                'name': 'ER',
                'subreport_id': ref('canada_mis_report.income_statement_summary'),
            }),
        ]"/>
        <field name="kpi_ids" eval="[
            (5, 0),
            (0, 0, {
                'name': 'TITLE_ASSETS',
                'description': 'Assets',
                'expression': 'AccountingNone',
                'style_id': ref('canada_mis_report.style_h1'),
                'accumulation_method': 'sum',
                'compare_method': 'pct',
                'type': 'num',
                'auto_expand_accounts': False,
            }),
            (0, 0, {
                'name': 'LIQUIDITY',
                'description': 'Liquidity',
                'expression': 'bale[(&#34;account_type&#34;, &#34;=&#34;, &#34;asset_cash&#34;)][]',
                'style_id': ref('canada_mis_report.style_h3'),
                'accumulation_method': 'sum',
                'compare_method': 'pct',
                'type': 'num',
                'auto_expand_accounts': True,
                'auto_expand_accounts_style_id': ref('canada_mis_report.style_detail'),
            }),
            (0, 0, {
                'name': 'RECEIVABLE',
                'description': 'Accounts Receivable',
                'expression': 'bale[(&#34;account_type&#34;, &#34;=&#34;, &#34;asset_receivable&#34;)][]',
                'style_id': ref('canada_mis_report.style_h3'),
                'accumulation_method': 'sum',
                'compare_method': 'pct',
                'type': 'num',
                'auto_expand_accounts': True,
                'auto_expand_accounts_style_id': ref('canada_mis_report.style_detail'),
            }),
            (0, 0, {
                'name': 'PRE_PAID_EXPENSES',
                'description': 'Pre-paid Expenses',
                'expression': 'bale[(&#34;account_type&#34;, &#34;=&#34;, &#34;asset_prepayments&#34;)][]',
                'style_id': ref('canada_mis_report.style_h3'),
                'accumulation_method': 'sum',
                'compare_method': 'pct',
                'type': 'num',
                'auto_expand_accounts': True,
                'auto_expand_accounts_style_id': ref('canada_mis_report.style_detail'),
            }),
            (0, 0, {
                'name': 'OTHER_CURRENT_ASSETS',
                'description': 'Other Current Assets',
                'expression': 'bale[(&#34;account_type&#34;, &#34;=&#34;, &#34;asset_current&#34;)][]',
                'style_id': ref('canada_mis_report.style_h3'),
                'accumulation_method': 'sum',
                'compare_method': 'pct',
                'type': 'num',
                'auto_expand_accounts': True,
                'auto_expand_accounts_style_id': ref('canada_mis_report.style_detail'),
            }),
            (0, 0, {
                'name': 'TOTAL_CURRENT_ASSETS',
                'description': 'Total Current Assets',
                'expression': 'LIQUIDITY + RECEIVABLE + PRE_PAID_EXPENSES + OTHER_CURRENT_ASSETS',
                'style_id': ref('canada_mis_report.style_h2'),
                'accumulation_method': 'sum',
                'compare_method': 'pct',
                'type': 'num',
                'auto_expand_accounts': False,
            }),
            (0, 0, {
                'name': 'FIXED_ASSETS',
                'description': 'Fixed Assets',
                'expression': 'bale[(&#34;account_type&#34;, &#34;=&#34;, &#34;asset_fixed&#34;)][]',
                'style_id': ref('canada_mis_report.style_h3'),
                'accumulation_method': 'sum',
                'compare_method': 'pct',
                'type': 'num',
                'auto_expand_accounts': True,
                'auto_expand_accounts_style_id': ref('canada_mis_report.style_detail'),
            }),
            (0, 0, {
                'name': 'OTHER_NON_CURRENT_ASSETS',
                'description': 'Other Non-current Assets',
                'expression': 'bale[(&#34;account_type&#34;, &#34;=&#34;, &#34;asset_non_current&#34;)][]',
                'style_id': ref('canada_mis_report.style_h3'),
                'accumulation_method': 'sum',
                'compare_method': 'pct',
                'type': 'num',
                'auto_expand_accounts': True,
                'auto_expand_accounts_style_id': ref('canada_mis_report.style_detail'),
            }),
            (0, 0, {
                'name': 'TOTAL_NON_CURRENT_ASSETS',
                'description': 'Total Non-current Assets',
                'expression': 'FIXED_ASSETS + OTHER_NON_CURRENT_ASSETS',
                'style_id': ref('canada_mis_report.style_h2'),
                'accumulation_method': 'sum',
                'compare_method': 'pct',
                'type': 'num',
                'auto_expand_accounts': False,
            }),
            (0, 0, {
                'name': 'TOTAL_ASSETS',
                'description': 'Total Assets',
                'expression': 'TOTAL_CURRENT_ASSETS + TOTAL_NON_CURRENT_ASSETS',
                'style_id': ref('canada_mis_report.style_h1'),
                'accumulation_method': 'sum',
                'compare_method': 'pct',
                'type': 'num',
                'auto_expand_accounts': False,
            }),
            (0, 0, {
                'name': '_8',
                'description': '-',
                'expression': 'AccountingNone',
                'accumulation_method': 'sum',
                'compare_method': 'pct',
                'type': 'num',
                'auto_expand_accounts': False,
            }),
            (0, 0, {
                'name': 'TITLE_LIABILITIES',
                'description': 'Liabilities',
                'expression': 'AccountingNone',
                'style_id': ref('canada_mis_report.style_h1'),
                'accumulation_method': 'sum',
                'compare_method': 'pct',
                'type': 'num',
                'auto_expand_accounts': False,
            }),
            (0, 0, {
                'name': 'PAYABLE',
                'description': 'Accounts Payable',
                'expression': '-bale[(&#34;account_type&#34;, &#34;=&#34;, &#34;liability_payable&#34;)][]',
                'style_id': ref('canada_mis_report.style_h3'),
                'accumulation_method': 'sum',
                'compare_method': 'pct',
                'type': 'num',
                'auto_expand_accounts': True,
                'auto_expand_accounts_style_id': ref('canada_mis_report.style_detail'),
            }),
            (0, 0, {
                'name': 'CREDIT_CARDS',
                'description': 'Credit Cards',
                'expression': '-bale[(&#34;account_type&#34;, &#34;=&#34;, &#34;liability_credit_card&#34;)][]',
                'style_id': ref('canada_mis_report.style_h3'),
                'accumulation_method': 'sum',
                'compare_method': 'pct',
                'type': 'num',
                'auto_expand_accounts': True,
                'auto_expand_accounts_style_id': ref('canada_mis_report.style_detail'),
            }),
            (0, 0, {
                'name': 'OTHER_CURRENT_LIABILITIES',
                'description': 'Other Current Liabilities',
                'expression': '-bale[(&#34;account_type&#34;, &#34;=&#34;, &#34;liability_current&#34;)][]',
                'style_id': ref('canada_mis_report.style_h3'),
                'accumulation_method': 'sum',
                'compare_method': 'pct',
                'type': 'num',
                'auto_expand_accounts': True,
                'auto_expand_accounts_style_id': ref('canada_mis_report.style_detail'),
            }),
            (0, 0, {
                'name': 'NON_CURRENT_LIABILITIES',
                'description': 'Non-current Liabilities',
                'expression': '-bale[(&#34;account_type&#34;, &#34;=&#34;, &#34;liability_non_current&#34;)][]',
                'style_id': ref('canada_mis_report.style_h3'),
                'accumulation_method': 'sum',
                'compare_method': 'pct',
                'type': 'num',
                'auto_expand_accounts': True,
                'auto_expand_accounts_style_id': ref('canada_mis_report.style_detail'),
            }),
            (0, 0, {
                'name': 'TOTAL_LIABILITIES',
                'description': 'Total Liabilities',
                'expression': 'PAYABLE + CREDIT_CARDS + OTHER_CURRENT_LIABILITIES + NON_CURRENT_LIABILITIES',
                'style_id': ref('canada_mis_report.style_h2'),
                'accumulation_method': 'sum',
                'compare_method': 'pct',
                'type': 'num',
                'auto_expand_accounts': False,
            }),
            (0, 0, {
                'name': '_10',
                'description': '-',
                'expression': 'AccountingNone',
                'accumulation_method': 'sum',
                'compare_method': 'pct',
                'type': 'num',
                'auto_expand_accounts': False,
            }),
            (0, 0, {
                'name': 'TITLE_EQUITY',
                'description': 'Equity',
                'expression': 'AccountingNone',
                'style_id': ref('canada_mis_report.style_h1'),
                'accumulation_method': 'sum',
                'compare_method': 'pct',
                'type': 'num',
                'auto_expand_accounts': False,
            }),
            (0, 0, {
                'name': 'EQUITY',
                'description': 'Equity and Previous Years Retained Earnings',
                'expression': '-bale[(&#34;account_type&#34;, &#34;in&#34;, (&#34;equity&#34;, &#34;equity_unaffected&#34;))][]',
                'style_id': ref('canada_mis_report.style_h3'),
                'accumulation_method': 'sum',
                'compare_method': 'pct',
                'type': 'num',
                'auto_expand_accounts': True,
                'auto_expand_accounts_style_id': ref('canada_mis_report.style_detail'),
            }),
            (0, 0, {
                'name': 'UNDEFERRED_RESULT_CURRENT',
                'description': 'Undeferred Profit And Loss - Current Year',
                'expression': 'YEAR_RESULT + RESULT_REPORTED',
                'style_id': ref('canada_mis_report.style_h3'),
                'accumulation_method': 'sum',
                'compare_method': 'pct',
                'type': 'num',
                'auto_expand_accounts': False,
            }),
            (0, 0, {
                'name': 'YEAR_RESULT',
                'description': 'Year Result',
                'expression': 'ER.NET_PROFIT',
                'style_id': ref('canada_mis_report.style_detail'),
                'accumulation_method': 'sum',
                'compare_method': 'pct',
                'type': 'num',
                'auto_expand_accounts': False,
            }),
            (0, 0, {
                'name': 'RESULT_REPORTED',
                'description': 'Deferred Results',
                'expression': '-balp[(&#34;account_type&#34;, &#34;=&#34;, &#34;equity_unaffected&#34;)][]',
                'style_id': ref('canada_mis_report.style_detail'),
                'accumulation_method': 'sum',
                'compare_method': 'pct',
                'type': 'num',
                'auto_expand_accounts': False,
            }),
            (0, 0, {
                'name': 'TOTAL_EQUITY',
                'description': 'Total Equity',
                'expression': 'EQUITY + UNDEFERRED_RESULT_CURRENT',
                'style_id': ref('canada_mis_report.style_h2'),
                'accumulation_method': 'sum',
                'compare_method': 'pct',
                'type': 'num',
                'auto_expand_accounts': False,
            }),
            (0, 0, {
                'name': 'TOTAL_EQUITY_LIABILITIES',
                'description': 'Total Equity And Liabilities',
                'expression': 'TOTAL_EQUITY + TOTAL_LIABILITIES',
                'style_id': ref('canada_mis_report.style_h1'),
                'accumulation_method': 'sum',
                'compare_method': 'pct',
                'type': 'num',
                'auto_expand_accounts': False,
            }),
        ]"/>
    </record>

    <!-- New records to add -->
    <record id="bank_reconciliation" model="mis.report">
        <field name="name">Bank Reconciliation</field>
        <field name="description">Bank Reconciliation</field>
        <field name="kpi_ids" eval="[
            (5, 0),
            (0, 0, {
                'name': 'PAYMENT_LINE_NO_STATEMENT',
                'description': 'Payments not linked to a transaction',
                'expression': 'crdp[(&#34;account_type&#34;, &#34;=&#34;, &#34;asset_cash&#34;)][(&#34;statement_line_id&#34;, &#34;=&#34;, False)]',
                'style_id': ref('canada_mis_report.style_h2'),
                'accumulation_method': 'sum',
                'compare_method': 'pct',
                'type': 'num',
                'auto_expand_accounts': True,
                'auto_expand_accounts_style_id': ref('canada_mis_report.style_detail'),
            }),
            (0, 0, {
                'name': 'ENCASHMENT_LINE_NO_STATEMENT',
                'description': 'Encashments not linked to a transaction',
                'expression': 'debp[(&#34;account_type&#34;, &#34;=&#34;, &#34;asset_cash&#34;)][(&#34;statement_line_id&#34;, &#34;=&#34;, False)]',
                'style_id': ref('canada_mis_report.style_h2'),
                'accumulation_method': 'sum',
                'compare_method': 'pct',
                'type': 'num',
                'auto_expand_accounts': True,
                'auto_expand_accounts_style_id': ref('canada_mis_report.style_detail'),
            }),
            (0, 0, {
                'name': 'BANK_OP_NO_ACCOUNT_LINE',
                'description': 'Bank transactions not linked to a journal entry',
                'expression': 'BANK_OP.amount',
                'style_id': ref('canada_mis_report.style_h2'),
                'accumulation_method': 'sum',
                'compare_method': 'pct',
                'type': 'num',
                'auto_expand_accounts': True,
                'auto_expand_accounts_style_id': ref('canada_mis_report.style_detail'),
            }),
        ]"/>
        <field name="query_ids" eval="[
            (5, 0),
            (0, 0, {
                'name': 'BANK_OP',
                'model_id': ref('account.model_account_bank_statement_line'),
                'field_ids': [(4, ref('account.field_account_bank_statement_line__amount'))],
                'date_field': ref('account.field_account_bank_statement_line__date'),
                'domain': '[(&#34;journal_entry_ids&#34;, &#34;=&#34;, False)]',
                'aggregate': 'sum',
            }),
        ]"/>
    </record>

    <record id="tax_report" model="mis.report">
        <field name="name">Tax Report</field>
        <field name="description">Tax Report</field>
        <field name="kpi_ids" eval="[
            (5, 0),
            (0, 0, {
                'name': 'INC',
                'description': 'Turnover',
                'expression': '-bal[(&#34;account_type&#34;, &#34;=&#34;, &#34;income&#34;)][]',
                'style_id': ref('canada_mis_report.style_h2'),
                'accumulation_method': 'sum',
                'compare_method': 'pct',
                'type': 'num',
                'auto_expand_accounts': False,
            }),
            (0, 0, {
                'name': '_3',
                'description': '-',
                'expression': 'AccountingNone',
                'style_id': False,
                'accumulation_method': 'sum',
                'compare_method': 'pct',
                'type': 'num',
                'auto_expand_accounts': False,
            }),
            (0, 0, {
                'name': 'GST_DECLA',
                'description': 'GST declaration over the period',
                'expression': 'AccountingNone',
                'style_id': ref('canada_mis_report.style_h2'),
                'accumulation_method': 'sum',
                'compare_method': 'pct',
                'type': 'num',
                'auto_expand_accounts': False,
            }),
            (0, 0, {
                'name': 'GST_SALE',
                'description': 'GST collected on sales',
                'expression': '-bal[(&#34;id&#34;, &#34;=&#34;, &#34;l10n_ca.chart2131_en&#34;)][]',
                'style_id': ref('canada_mis_report.style_h3'),
                'accumulation_method': 'sum',
                'compare_method': 'pct',
                'type': 'num',
                'auto_expand_accounts': False,
            }),
            (0, 0, {
                'name': 'GST_PURC',
                'description': 'GST paid on Purchases',
                'expression': 'bal[(&#34;id&#34;, &#34;=&#34;, &#34;l10n_ca.chart1181_en&#34;)][]',
                'style_id': ref('canada_mis_report.style_h3'),
                'accumulation_method': 'sum',
                'compare_method': 'pct',
                'type': 'num',
                'auto_expand_accounts': False,
            }),
            (0, 0, {
                'name': 'GST_BALANCE',
                'description': 'GST Balance',
                'expression': 'GST_SALE - GST_PURC',
                'style_id': ref('canada_mis_report.style_h3'),
                'accumulation_method': 'sum',
                'compare_method': 'pct',
                'type': 'num',
                'auto_expand_accounts': False,
            }),
            (0, 0, {
                'name': '_2',
                'description': '-',
                'expression': 'AccountingNone',
                'style_id': False,
                'accumulation_method': 'sum',
                'compare_method': 'pct',
                'type': 'num',
                'auto_expand_accounts': False,
            }),
            (0, 0, {
                'name': 'QST_DECLA',
                'description': 'QST declaration for the period',
                'expression': 'AccountingNone',
                'style_id': ref('canada_mis_report.style_h2'),
                'accumulation_method': 'sum',
                'compare_method': 'pct',
                'type': 'num',
                'auto_expand_accounts': False,
            }),
            (0, 0, {
                'name': 'QST_SALE',
                'description': 'QST collected on sales',
                'expression': '-bal[(&#34;id&#34;, &#34;=&#34;, &#34;l10n_ca.chart2132_en&#34;)][]',
                'style_id': ref('canada_mis_report.style_h3'),
                'accumulation_method': 'sum',
                'compare_method': 'pct',
                'type': 'num',
                'auto_expand_accounts': False,
            }),
            (0, 0, {
                'name': 'QST_PURC',
                'description': 'QST paid on Purchases',
                'expression': 'bal[(&#34;id&#34;, &#34;=&#34;, &#34;l10n_ca.chart1182_en&#34;)][]',
                'style_id': ref('canada_mis_report.style_h3'),
                'accumulation_method': 'sum',
                'compare_method': 'pct',
                'type': 'num',
                'auto_expand_accounts': False,
            }),
            (0, 0, {
                'name': 'QST_BALANCE',
                'description': 'QST balance',
                'expression': 'QST_SALE - QST_PURC',
                'style_id': ref('canada_mis_report.style_h3'),
                'accumulation_method': 'sum',
                'compare_method': 'pct',
                'type': 'num',
                'auto_expand_accounts': False,
            }),
            (0, 0, {
                'name': '_4',
                'description': '-',
                'expression': 'AccountingNone',
                'style_id': False,
                'accumulation_method': 'sum',
                'compare_method': 'pct',
                'type': 'num',
                'auto_expand_accounts': False,
            }),
            (0, 0, {
                'name': 'TOTAL_SALE',
                'description': 'Total taxes collected on Sales',
                'expression': 'GST_SALE + QST_SALE',
                'style_id': ref('canada_mis_report.style_h2'),
                'accumulation_method': 'sum',
                'compare_method': 'pct',
                'type': 'num',
                'auto_expand_accounts': False,
            }),
            (0, 0, {
                'name': 'TOTAL_PURC',
                'description': 'Total Taxes Paid on Purchases',
                'expression': 'GST_PURC + QST_PURC',
                'style_id': ref('canada_mis_report.style_h2'),
                'accumulation_method': 'sum',
                'compare_method': 'pct',
                'type': 'num',
                'auto_expand_accounts': False,
            }),
            (0, 0, {
                'name': 'BALANCE',
                'description': 'Balance payable',
                'expression': 'GST_BALANCE + QST_BALANCE',
                'style_id': ref('canada_mis_report.style_h2'),
                'accumulation_method': 'sum',
                'compare_method': 'pct',
                'type': 'num',
                'auto_expand_accounts': False,
            }),
            (0, 0, {
                'name': '_6',
                'description': '-',
                'expression': 'AccountingNone',
                'style_id': False,
                'accumulation_method': 'sum',
                'compare_method': 'pct',
                'type': 'num',
                'auto_expand_accounts': False,
            }),
            (0, 0, {
                'name': 'CTRL',
                'description': 'Controls',
                'expression': 'AccountingNone',
                'style_id': ref('canada_mis_report.style_h2'),
                'accumulation_method': 'sum',
                'compare_method': 'pct',
                'type': 'num',
                'auto_expand_accounts': False,
            }),
            (0, 0, {
                'name': 'CTRL_GST_SALE',
                'description': 'Accumulated balance - GST collected',
                'expression': '-bale[(&#34;id&#34;, &#34;=&#34;, &#34;l10n_ca.chart2131_en&#34;)][]',
                'style_id': ref('canada_mis_report.style_h3'),
                'accumulation_method': 'sum',
                'compare_method': 'pct',
                'type': 'num',
                'auto_expand_accounts': False,
            }),
            (0, 0, {
                'name': 'CTRL_GST_PURC',
                'description': 'Accumulated balance - GST paid',
                'expression': 'bale[(&#34;id&#34;, &#34;=&#34;, &#34;l10n_ca.chart1181_en&#34;)][]',
                'style_id': ref('canada_mis_report.style_h3'),
                'accumulation_method': 'sum',
                'compare_method': 'pct',
                'type': 'num',
                'auto_expand_accounts': False,
            }),
            (0, 0, {
                'name': 'SS_TOT_GST',
                'description': 'GST accumulated balance',
                'expression': 'CTRL_GST_SALE - CTRL_GST_PURC',
                'style_id': ref('canada_mis_report.style_h2'),
                'accumulation_method': 'sum',
                'compare_method': 'pct',
                'type': 'num',
                'auto_expand_accounts': False,
            }),
            (0, 0, {
                'name': 'DIFF_GST',
                'description': 'Difference on GST',
                'expression': 'GST_BALANCE - SS_TOT_GST',
                'style_id': ref('canada_mis_report.style_h2'),
                'accumulation_method': 'sum',
                'compare_method': 'pct',
                'type': 'num',
                'auto_expand_accounts': False,
            }),
            (0, 0, {
                'name': '_6',
                'description': '-',
                'expression': 'AccountingNone',
                'style_id': False,
                'accumulation_method': 'sum',
                'compare_method': 'pct',
                'type': 'num',
                'auto_expand_accounts': False,
            }),
            (0, 0, {
                'name': 'CTRL_QST_SALE',
                'description': 'Accumulated balance - QST collected',
                'expression': '-bale[(&#34;id&#34;, &#34;=&#34;, &#34;l10n_ca.chart2132_en&#34;)][]',
                'style_id': ref('canada_mis_report.style_h3'),
                'accumulation_method': 'sum',
                'compare_method': 'pct',
                'type': 'num',
                'auto_expand_accounts': False,
            }),
            (0, 0, {
                'name': 'CTRL_QST_PURC',
                'description': 'Accumulated balance - QST paid',
                'expression': 'bale[(&#34;id&#34;, &#34;=&#34;, &#34;l10n_ca.chart1182_en&#34;)][]',
                'style_id': ref('canada_mis_report.style_h3'),
                'accumulation_method': 'sum',
                'compare_method': 'pct',
                'type': 'num',
                'auto_expand_accounts': False,
            }),
            (0, 0, {
                'name': 'SS_TOT_QST',
                'description': 'QST accumulated balance',
                'expression': 'CTRL_QST_SALE - CTRL_QST_PURC',
                'style_id': ref('canada_mis_report.style_h2'),
                'accumulation_method': 'sum',
                'compare_method': 'pct',
                'type': 'num',
                'auto_expand_accounts': False,
            }),
            (0, 0, {
                'name': 'DIFF_QST',
                'description': 'Difference on QST',
                'expression': 'QST_BALANCE - SS_TOT_QST',
                'style_id': ref('canada_mis_report.style_h3'),
                'accumulation_method': 'sum',
                'compare_method': 'pct',
                'type': 'num',
                'auto_expand_accounts': False,
            }),
        ]"/>
    </record>

    <function model="mis.report" name="translate_canada_reports"/>

</odoo>
